README.md
setup.py
airbench/__init__.py
airbench/lib_airbench93.py
airbench/lib_airbench94.py
airbench/lib_airbench95.py
airbench/lib_airbench96.py
airbench/utils.py
airbench.egg-info/PKG-INFO
airbench.egg-info/SOURCES.txt
airbench.egg-info/dependency_links.txt
airbench.egg-info/top_level.txt